krxholiday
