Metadata-Version: 1.0
Name: krxholiday
Version: 1.0
Summary: krxholiday
Home-page: UNKNOWN
Author: shhong
Author-email: shhong@mirib.net
License: UNKNOWN
Platform: UNKNOWN
